gamebyte_agent/__init__.py
gamebyte_agent/app.py
gamebyte_agent/config.py
gamebyte_agent/console.py
gamebyte_agent/context.py
gamebyte_agent/context_dependent.py
gamebyte_agent/event_progress.py
gamebyte_agent/mcp_server_registry.py
gamebyte_agent/progress_display.py
gamebyte_agent/agents/__init__.py
gamebyte_agent/agents/agent.py
gamebyte_agent/agents/base_agent.py
gamebyte_agent/agents/workflow/__init__.py
gamebyte_agent/agents/workflow/chain_agent.py
gamebyte_agent/agents/workflow/evaluator_optimizer.py
gamebyte_agent/agents/workflow/orchestrator_agent.py
gamebyte_agent/agents/workflow/orchestrator_models.py
gamebyte_agent/agents/workflow/orchestrator_prompts.py
gamebyte_agent/agents/workflow/parallel_agent.py
gamebyte_agent/agents/workflow/router_agent.py
gamebyte_agent/cli/__init__.py
gamebyte_agent/cli/__main__.py
gamebyte_agent/cli/main.py
gamebyte_agent/cli/terminal.py
gamebyte_agent/cli/commands/bootstrap.py
gamebyte_agent/cli/commands/config.py
gamebyte_agent/cli/commands/setup.py
gamebyte_agent/core/__init__.py
gamebyte_agent/core/agent_app.py
gamebyte_agent/core/agent_types.py
gamebyte_agent/core/direct_decorators.py
gamebyte_agent/core/direct_factory.py
gamebyte_agent/core/enhanced_prompt.py
gamebyte_agent/core/error_handling.py
gamebyte_agent/core/exceptions.py
gamebyte_agent/core/fastagent.py
gamebyte_agent/core/interactive_prompt.py
gamebyte_agent/core/mcp_content.py
gamebyte_agent/core/prompt.py
gamebyte_agent/core/request_params.py
gamebyte_agent/core/validation.py
gamebyte_agent/executor/__init__.py
gamebyte_agent/executor/decorator_registry.py
gamebyte_agent/executor/executor.py
gamebyte_agent/executor/task_registry.py
gamebyte_agent/executor/temporal.py
gamebyte_agent/executor/workflow.py
gamebyte_agent/executor/workflow_signal.py
gamebyte_agent/human_input/__init__.py
gamebyte_agent/human_input/handler.py
gamebyte_agent/human_input/types.py
gamebyte_agent/llm/__init__.py
gamebyte_agent/llm/augmented_llm.py
gamebyte_agent-0.1.0.dist-info/METADATA
gamebyte_agent-0.1.0.dist-info/WHEEL
gamebyte_agent-0.1.0.dist-info/entry_points.txt
gamebyte_agent-0.1.0.dist-info/licenses/LICENSE
gamebyte_agent-0.1.0.dist-info/RECORD
