Metadata-Version: 2.4
Name: gamebyte-agent
Version: 0.1.0
Summary: Define, Prompt and Test MCP enabled Agents and Workflows with OpenRouter support
Author-email: Shaun Smith <fastagent@llmindset.co.uk>, Sarmad Qadri <sarmad@lastmileai.dev>
License:                                  Apache License
License-File: LICENSE
Classifier: License :: OSI Approved :: Apache Software License
Classifier: Operating System :: OS Independent
Classifier: Programming Language :: Python :: 3
Requires-Python: >=3.10
Requires-Dist: aiohttp>=3.11.13
Requires-Dist: anthropic>=0.49.0
Requires-Dist: fastapi>=0.115.6
Requires-Dist: mcp==1.6.0
Requires-Dist: numpy>=2.2.1
Requires-Dist: openai>=1.63.2
Requires-Dist: opentelemetry-distro>=0.50b0
Requires-Dist: opentelemetry-exporter-otlp-proto-http>=1.29.0
Requires-Dist: prompt-toolkit>=3.0.50
Requires-Dist: pydantic-settings>=2.7.0
Requires-Dist: pydantic>=2.10.4
Requires-Dist: pyyaml>=6.0.2
Requires-Dist: rich>=13.9.4
Requires-Dist: scikit-learn>=1.6.0
Requires-Dist: typer>=0.15.1
Provides-Extra: dev
Requires-Dist: anthropic>=0.42.0; extra == 'dev'
Requires-Dist: pre-commit>=4.0.1; extra == 'dev'
Requires-Dist: pydantic>=2.10.4; extra == 'dev'
Requires-Dist: pytest-asyncio>=0.21.1; extra == 'dev'
Requires-Dist: pytest-cov; extra == 'dev'
Requires-Dist: pytest>=7.4.0; extra == 'dev'
Requires-Dist: pyyaml>=6.0.2; extra == 'dev'
Requires-Dist: ruff>=0.8.4; extra == 'dev'
Requires-Dist: tomli>=2.2.1; extra == 'dev'
Provides-Extra: openai
Requires-Dist: openai>=1.58.1; extra == 'openai'
Provides-Extra: temporal
Requires-Dist: temporalio>=1.8.0; extra == 'temporal'
